scrapy_eagle/__init__.py
scrapy_eagle/dashboard/__init__.py
scrapy_eagle/dashboard/config.py
scrapy_eagle/dashboard/generator.py
scrapy_eagle/dashboard/main.py
scrapy_eagle/dashboard/memory.py
scrapy_eagle/dashboard/server.py
scrapy_eagle/dashboard/settings.py
scrapy_eagle/dashboard/green_threads/__init__.py
scrapy_eagle/dashboard/green_threads/executor.py
scrapy_eagle/dashboard/green_threads/heartbeat.py
scrapy_eagle/dashboard/green_threads/stats.py
scrapy_eagle/dashboard/templates/index.html
scrapy_eagle/dashboard/templates/static/css/bundle.css
scrapy_eagle/dashboard/templates/static/css/bundle.css.map
scrapy_eagle/dashboard/templates/static/css/main.css
scrapy_eagle/dashboard/templates/static/img/system-logo.jpg
scrapy_eagle/dashboard/templates/static/js/bundle.js
scrapy_eagle/dashboard/templates/static/js/bundle.js.map
scrapy_eagle/dashboard/templates/static/js/main.js
scrapy_eagle/dashboard/templates/static/js/vendor/jquery.navgoco.min.js
scrapy_eagle/dashboard/utils/__init__.py
scrapy_eagle/dashboard/utils/commandskit.py
scrapy_eagle/dashboard/utils/ip.py
scrapy_eagle/dashboard/utils/process.py
scrapy_eagle/dashboard/utils/processkit.py
scrapy_eagle/dashboard/utils/spiderskit.py
scrapy_eagle/dashboard/views/__init__.py
scrapy_eagle/dashboard/views/jobs.py
scrapy_eagle/dashboard/views/processes.py
scrapy_eagle/dashboard/views/react_app.py
scrapy_eagle/dashboard/views/root.py
scrapy_eagle/dashboard/views/servers.py
scrapy_eagle/dashboard/views/spiders.py
scrapy_eagle/worker/__init__.py
scrapy_eagle/worker/connection.py
scrapy_eagle/worker/dupefilter.py
scrapy_eagle/worker/picklecompat.py
scrapy_eagle/worker/queue.py
scrapy_eagle/worker/scheduler.py
scrapy_eagle/worker/spiders.py
scrapy_eagle-0.0.37.dist-info/DESCRIPTION.rst
scrapy_eagle-0.0.37.dist-info/METADATA
scrapy_eagle-0.0.37.dist-info/RECORD
scrapy_eagle-0.0.37.dist-info/WHEEL
scrapy_eagle-0.0.37.dist-info/entry_points.txt
scrapy_eagle-0.0.37.dist-info/metadata.json
scrapy_eagle-0.0.37.dist-info/top_level.txt
