Metadata-Version: 2.0
Name: scrapy-eagle
Version: 0.0.37
Summary: Run Scrapy Distributed
Home-page: http://github.com/rafaelcapucho/scrapy-eagle
Author: Rafael Alfredo Capucho
Author-email: rafael.capucho@gmail.com
License: BSD
Platform: UNKNOWN
Classifier: Development Status :: 3 - Alpha
Classifier: Framework :: Scrapy
Classifier: Programming Language :: Python
Classifier: Programming Language :: Python :: 3.5
Classifier: Intended Audience :: Developers
Requires-Dist: flask
Requires-Dist: flask-cors
Requires-Dist: flask-socketio
Requires-Dist: gevent
Requires-Dist: psutil
Requires-Dist: pymongo
Requires-Dist: redis
Requires-Dist: requests
Requires-Dist: scrapy (>=1.1.0)
